{
    "originalImage": "/Users/melaniemadrigal/Desktop/Plate3/C5_008.tif",
    "timestamp": 8,
    "sample": "C5",
    "sclerotiaPrimordia": {
        "skeleton": "/Users/melaniemadrigal/Desktop/Skeleton3/C5_008_sclerotiaPrimordia.tif",
        "vectorized": {
            "lines": [
                [
                    0,
                    1,
                    2
                ],
                [
                    2,
                    3,
                    5
                ],
                [
                    2,
                    6
                ],
                [
                    4,
                    7,
                    9,
                    11,
                    12
                ],
                [
                    5,
                    8,
                    10
                ],
                [
                    14,
                    16,
                    17
                ],
                [
                    17,
                    18,
                    19
                ],
                [
                    20,
                    21,
                    22,
                    23,
                    24,
                    25,
                    26
                ],
                [
                    29,
                    30,
                    31,
                    32,
                    33,
                    34
                ],
                [
                    34,
                    36,
                    37,
                    38,
                    39,
                    40,
                    41,
                    42,
                    43
                ],
                [
                    44,
                    45,
                    46,
                    47,
                    48,
                    49,
                    50,
                    51,
                    52
                ],
                [
                    52,
                    53,
                    55,
                    61
                ],
                [
                    52,
                    54
                ],
                [
                    54,
                    57,
                    60,
                    62
                ],
                [
                    54,
                    56,
                    58,
                    59
                ],
                [
                    61,
                    63,
                    65,
                    69,
                    70,
                    71,
                    72
                ],
                [
                    61,
                    64,
                    62
                ],
                [
                    62,
                    66,
                    67,
                    68
                ],
                [
                    82,
                    81,
                    80,
                    79,
                    78,
                    76,
                    75,
                    73,
                    74,
                    77
                ],
                [
                    83,
                    84,
                    85,
                    86,
                    87
                ],
                [
                    87,
                    88,
                    89,
                    92,
                    94,
                    95
                ],
                [
                    87,
                    90
                ],
                [
                    90,
                    93
                ],
                [
                    96,
                    97,
                    98
                ],
                [
                    98,
                    101
                ],
                [
                    100,
                    102,
                    103,
                    105
                ],
                [
                    101,
                    104,
                    106,
                    107,
                    108,
                    109
                ],
                [
                    110,
                    111,
                    112,
                    113,
                    114
                ],
                [
                    116,
                    117
                ],
                [
                    117,
                    119,
                    121
                ],
                [
                    118,
                    120,
                    122
                ],
                [
                    122,
                    124,
                    125
                ],
                [
                    122,
                    123,
                    125
                ],
                [
                    125,
                    126
                ],
                [
                    127,
                    128,
                    129,
                    130,
                    131,
                    132,
                    133,
                    134
                ],
                [
                    134,
                    136,
                    138
                ],
                [
                    134,
                    135,
                    137
                ],
                [
                    137,
                    139,
                    140,
                    141,
                    142,
                    143,
                    144
                ],
                [
                    145,
                    146,
                    147
                ],
                [
                    147,
                    149,
                    151
                ],
                [
                    147,
                    150
                ],
                [
                    147,
                    148,
                    150
                ],
                [
                    150,
                    152
                ],
                [
                    153,
                    156
                ],
                [
                    150,
                    159,
                    162
                ],
                [
                    150,
                    154,
                    157
                ],
                [
                    155,
                    160,
                    164,
                    169,
                    171,
                    176,
                    179,
                    180
                ],
                [
                    155,
                    158,
                    157
                ],
                [
                    156,
                    161,
                    165
                ],
                [
                    157,
                    166
                ],
                [
                    165,
                    167,
                    170,
                    174,
                    178
                ],
                [
                    165,
                    173
                ],
                [
                    168,
                    172,
                    175,
                    181
                ],
                [
                    168,
                    177
                ],
                [
                    183,
                    184,
                    185
                ],
                [
                    185,
                    186,
                    187,
                    188,
                    189,
                    190
                ],
                [
                    191,
                    192,
                    193,
                    194
                ],
                [
                    194,
                    195,
                    198
                ],
                [
                    194,
                    197,
                    201
                ],
                [
                    199,
                    202,
                    205,
                    206,
                    207,
                    208
                ],
                [
                    200,
                    203,
                    204
                ],
                [
                    209,
                    210,
                    211,
                    212,
                    213,
                    214,
                    215,
                    216,
                    217,
                    218
                ],
                [
                    218,
                    221,
                    224
                ],
                [
                    218,
                    219,
                    220
                ],
                [
                    220,
                    225,
                    226,
                    229
                ],
                [
                    220,
                    223,
                    227,
                    228
                ],
                [
                    230,
                    231,
                    232,
                    233,
                    234,
                    235,
                    236,
                    237,
                    238,
                    239
                ],
                [
                    239,
                    240,
                    241,
                    242,
                    243,
                    244,
                    245,
                    246
                ],
                [
                    247,
                    248,
                    249,
                    250
                ],
                [
                    257,
                    258
                ],
                [
                    258,
                    259,
                    260,
                    261
                ],
                [
                    261,
                    262,
                    265
                ],
                [
                    261,
                    263,
                    264,
                    266,
                    265
                ],
                [
                    265,
                    267,
                    269,
                    271
                ],
                [
                    265,
                    270,
                    271
                ],
                [
                    272,
                    276,
                    279,
                    282
                ],
                [
                    273,
                    274,
                    277,
                    278
                ],
                [
                    278,
                    280,
                    281,
                    284
                ],
                [
                    278,
                    283,
                    285
                ],
                [
                    286,
                    287,
                    288,
                    289,
                    290
                ],
                [
                    290,
                    291,
                    293
                ],
                [
                    295,
                    297,
                    298
                ],
                [
                    295,
                    296,
                    299,
                    300,
                    301,
                    302
                ]
            ],
            "points": [
                [
                    0.5697791164658634,
                    0.998995983935743
                ],
                [
                    0.5687751004016064,
                    0.9849397590361446
                ],
                [
                    0.5746736947791165,
                    0.9662399598393574
                ],
                [
                    0.5803212851405622,
                    0.9653614457831325
                ],
                [
                    0.5732931726907631,
                    0.9590863453815262
                ],
                [
                    0.5798192771084337,
                    0.9583333333333334
                ],
                [
                    0.5645080321285141,
                    0.9658634538152611
                ],
                [
                    0.5632530120481928,
                    0.9563253012048193
                ],
                [
                    0.5763052208835341,
                    0.9492971887550201
                ],
                [
                    0.5567269076305221,
                    0.9598393574297188
                ],
                [
                    0.5707831325301205,
                    0.9442771084337349
                ],
                [
                    0.5507028112449799,
                    0.9593373493975904
                ],
                [
                    0.5421686746987951,
                    0.9482931726907631
                ],
                [
                    0.8383534136546185,
                    0.9819277108433735
                ],
                [
                    0.8389809236947792,
                    0.9756526104417671
                ],
                [
                    0.8448795180722891,
                    0.9754016064257028
                ],
                [
                    0.8396084337349398,
                    0.9620983935742972
                ],
                [
                    0.8390227576974564,
                    0.9501338688085678
                ],
                [
                    0.8443775100401606,
                    0.947289156626506
                ],
                [
                    0.8438755020080321,
                    0.9432730923694779
                ],
                [
                    0.6531124497991968,
                    0.9809236947791165
                ],
                [
                    0.6581325301204819,
                    0.9713855421686747
                ],
                [
                    0.661144578313253,
                    0.9593373493975904
                ],
                [
                    0.6711847389558233,
                    0.9523092369477911
                ],
                [
                    0.678714859437751,
                    0.9407630522088354
                ],
                [
                    0.6872489959839357,
                    0.9342369477911646
                ],
                [
                    0.6909303882195449,
                    0.9255354752342703
                ],
                [
                    0.6832329317269076,
                    0.9211847389558233
                ],
                [
                    0.697289156626506,
                    0.9252008032128514
                ],
                [
                    0.8654618473895582,
                    0.9392570281124498
                ],
                [
                    0.8604417670682731,
                    0.9347389558232931
                ],
                [
                    0.8569277108433735,
                    0.9257028112449799
                ],
                [
                    0.8498995983935743,
                    0.9236947791164658
                ],
                [
                    0.8428714859437751,
                    0.9156626506024097
                ],
                [
                    0.829066265060241,
                    0.9113955823293173
                ],
                [
                    0.8268072289156626,
                    0.9176706827309237
                ],
                [
                    0.8187751004016064,
                    0.9031124497991968
                ],
                [
                    0.8122489959839357,
                    0.9011044176706827
                ],
                [
                    0.8087349397590361,
                    0.8970883534136547
                ],
                [
                    0.8082329317269076,
                    0.8885542168674698
                ],
                [
                    0.8112449799196787,
                    0.8800200803212852
                ],
                [
                    0.8107429718875502,
                    0.8744979919678715
                ],
                [
                    0.8057228915662651,
                    0.8594377510040161
                ],
                [
                    0.8012048192771084,
                    0.8559236947791165
                ],
                [
                    0.2419678714859438,
                    0.911144578313253
                ],
                [
                    0.24748995983935743,
                    0.9071285140562249
                ],
                [
                    0.24949799196787148,
                    0.9016064257028112
                ],
                [
                    0.2605421686746988,
                    0.8920682730923695
                ],
                [
                    0.26957831325301207,
                    0.8885542168674698
                ],
                [
                    0.28112449799196787,
                    0.8900602409638554
                ],
                [
                    0.2856425702811245,
                    0.8860441767068273
                ],
                [
                    0.29267068273092367,
                    0.8840361445783133
                ],
                [
                    0.30672690763052207,
                    0.8694779116465863
                ],
                [
                    0.3107429718875502,
                    0.8684738955823293
                ],
                [
                    0.3029618473895582,
                    0.8601907630522089
                ],
                [
                    0.3157630522088353,
                    0.8629518072289156
                ],
                [
                    0.29869477911646586,
                    0.858433734939759
                ],
                [
                    0.30622489959839355,
                    0.8559236947791165
                ],
                [
                    0.29518072289156627,
                    0.8544176706827309
                ],
                [
                    0.29066265060240964,
                    0.856425702811245
                ],
                [
                    0.3057228915662651,
                    0.8438755020080322
                ],
                [
                    0.3205321285140562,
                    0.8451305220883534
                ],
                [
                    0.3084839357429719,
                    0.8393574297188755
                ],
                [
                    0.3247991967871486,
                    0.839859437751004
                ],
                [
                    0.3130020080321285,
                    0.8403614457831325
                ],
                [
                    0.3293172690763052,
                    0.8373493975903614
                ],
                [
                    0.30522088353413657,
                    0.8318273092369478
                ],
                [
                    0.29819277108433734,
                    0.8253012048192772
                ],
                [
                    0.2936746987951807,
                    0.8177710843373494
                ],
                [
                    0.34839357429718876,
                    0.8122489959839357
                ],
                [
                    0.35642570281124497,
                    0.8062248995983936
                ],
                [
                    0.357429718875502,
                    0.8017068273092369
                ],
                [
                    0.3609437751004016,
                    0.7996987951807228
                ],
                [
                    0.4397590361445783,
                    0.8810240963855421
                ],
                [
                    0.4467871485943775,
                    0.8787650602409639
                ],
                [
                    0.4322289156626506,
                    0.875
                ],
                [
                    0.4282128514056225,
                    0.8744979919678715
                ],
                [
                    0.44779116465863456,
                    0.8729919678714859
                ],
                [
                    0.4252008032128514,
                    0.8689759036144579
                ],
                [
                    0.4181726907630522,
                    0.8619477911646587
                ],
                [
                    0.4171686746987952,
                    0.8579317269076305
                ],
                [
                    0.4071285140562249,
                    0.8524096385542168
                ],
                [
                    0.40612449799196787,
                    0.8478915662650602
                ],
                [
                    0.7896586345381527,
                    0.7113453815261044
                ],
                [
                    0.7916666666666666,
                    0.6967871485943775
                ],
                [
                    0.8097389558232931,
                    0.6802208835341366
                ],
                [
                    0.8157630522088354,
                    0.6711847389558233
                ],
                [
                    0.8285642570281124,
                    0.6586345381526104
                ],
                [
                    0.8258032128514057,
                    0.6521084337349398
                ],
                [
                    0.8217871485943775,
                    0.6511044176706827
                ],
                [
                    0.8438755020080322,
                    0.6621485943775101
                ],
                [
                    0.8423694779116466,
                    0.6551204819277108
                ],
                [
                    0.8122489959839357,
                    0.6551204819277108
                ],
                [
                    0.8438755020080321,
                    0.6726907630522088
                ],
                [
                    0.8092369477911646,
                    0.6606425702811245
                ],
                [
                    0.804718875502008,
                    0.6639056224899599
                ],
                [
                    0.9166666666666666,
                    0.7058232931726908
                ],
                [
                    0.9106425702811245,
                    0.7023092369477912
                ],
                [
                    0.8960843373493976,
                    0.6974146586345382
                ],
                [
                    0.89190093708166,
                    0.7028112449799196
                ],
                [
                    0.8899598393574297,
                    0.6954819277108434
                ],
                [
                    0.9051204819277109,
                    0.6880020080321285
                ],
                [
                    0.8895582329317269,
                    0.6827309236947792
                ],
                [
                    0.8850401606425703,
                    0.6807228915662651
                ],
                [
                    0.911144578313253,
                    0.6757028112449799
                ],
                [
                    0.8820281124497992,
                    0.6767068273092369
                ],
                [
                    0.9171686746987951,
                    0.6716867469879518
                ],
                [
                    0.9252008032128514,
                    0.6616465863453815
                ],
                [
                    0.9312248995983936,
                    0.6591365461847389
                ],
                [
                    0.9387550200803213,
                    0.6506024096385542
                ],
                [
                    0.46209839357429716,
                    0.6199799196787148
                ],
                [
                    0.4663654618473896,
                    0.6124497991967872
                ],
                [
                    0.4643574297188755,
                    0.6054216867469879
                ],
                [
                    0.4708835341365462,
                    0.6004016064257028
                ],
                [
                    0.4732262382864792,
                    0.5952141900937082
                ],
                [
                    0.47740963855421686,
                    0.5933734939759037
                ],
                [
                    0.8930722891566265,
                    0.5858433734939759
                ],
                [
                    0.8900602409638554,
                    0.5759036144578313
                ],
                [
                    0.893239625167336,
                    0.5714524765729585
                ],
                [
                    0.8785140562248996,
                    0.5753012048192772
                ],
                [
                    0.9016064257028112,
                    0.5662650602409638
                ],
                [
                    0.8795180722891567,
                    0.581074297188755
                ],
                [
                    0.9058734939759037,
                    0.5647590361445782
                ],
                [
                    0.9106425702811245,
                    0.5637550200803213
                ],
                [
                    0.9066265060240963,
                    0.5597389558232932
                ],
                [
                    0.9141566265060241,
                    0.5568942436412316
                ],
                [
                    0.9226907630522089,
                    0.5471887550200802
                ],
                [
                    0.6977911646586346,
                    0.5005020080321285
                ],
                [
                    0.6917670682730924,
                    0.4969879518072289
                ],
                [
                    0.679718875502008,
                    0.4969879518072289
                ],
                [
                    0.6752008032128514,
                    0.49347389558232935
                ],
                [
                    0.6681726907630522,
                    0.49397590361445787
                ],
                [
                    0.6641566265060241,
                    0.48895582329317266
                ],
                [
                    0.6566265060240963,
                    0.48544176706827313
                ],
                [
                    0.6553714859437751,
                    0.4781626506024096
                ],
                [
                    0.6493473895582329,
                    0.4764056224899599
                ],
                [
                    0.6641566265060241,
                    0.4764056224899599
                ],
                [
                    0.6489290495314591,
                    0.46770414993306564
                ],
                [
                    0.6716867469879518,
                    0.4723895582329317
                ],
                [
                    0.6380522088353414,
                    0.46837349397590367
                ],
                [
                    0.6295180722891566,
                    0.46285140562248994
                ],
                [
                    0.6204819277108434,
                    0.45331325301204817
                ],
                [
                    0.6159638554216867,
                    0.4523092369477911
                ],
                [
                    0.6124497991967871,
                    0.4487951807228916
                ],
                [
                    0.6044176706827309,
                    0.4357429718875502
                ],
                [
                    0.4422690763052209,
                    0.4668674698795181
                ],
                [
                    0.44929718875502006,
                    0.4598393574297188
                ],
                [
                    0.45130522088353414,
                    0.45368975903614456
                ],
                [
                    0.4568273092369478,
                    0.4508032128514057
                ],
                [
                    0.44252008032128515,
                    0.4538152610441767
                ],
                [
                    0.45674364123159306,
                    0.4432730923694779
                ],
                [
                    0.4362449799196787,
                    0.4598393574297188
                ],
                [
                    0.4442771084337349,
                    0.44728915662650603
                ],
                [
                    0.4489625167336011,
                    0.4399263721552879
                ],
                [
                    0.45532128514056225,
                    0.4367469879518072
                ],
                [
                    0.4626004016064257,
                    0.4354919678714859
                ],
                [
                    0.4467871485943775,
                    0.4299698795180723
                ],
                [
                    0.45324153757888697,
                    0.42771084337349397
                ],
                [
                    0.4608433734939759,
                    0.4312248995983936
                ],
                [
                    0.4708835341365462,
                    0.44528112449799195
                ],
                [
                    0.46937751004016065,
                    0.4337349397590361
                ],
                [
                    0.44126506024096385,
                    0.43222891566265065
                ],
                [
                    0.4713855421686747,
                    0.4523092369477911
                ],
                [
                    0.4603413654618474,
                    0.4236947791164659
                ],
                [
                    0.4748995983935743,
                    0.4236947791164659
                ],
                [
                    0.43498995983935745,
                    0.4332329317269076
                ],
                [
                    0.44854417670682734,
                    0.4174196787148594
                ],
                [
                    0.4342369477911647,
                    0.4292168674698795
                ],
                [
                    0.4441934404283802,
                    0.41415662650602414
                ],
                [
                    0.48493975903614456,
                    0.42018072289156627
                ],
                [
                    0.42720883534136544,
                    0.42520080321285136
                ],
                [
                    0.4899598393574297,
                    0.4156626506024096
                ],
                [
                    0.4497991967871486,
                    0.4031124497991968
                ],
                [
                    0.43022088353413657,
                    0.4518072289156626
                ],
                [
                    0.42319277108433734,
                    0.4156626506024096
                ],
                [
                    0.44929718875502006,
                    0.3975903614457831
                ],
                [
                    0.49698795180722893,
                    0.41465863453815266
                ],
                [
                    0.42595381526104414,
                    0.4061244979919679
                ],
                [
                    0.4146586345381526,
                    0.41164658634538154
                ],
                [
                    0.5030120481927711,
                    0.4076305220883534
                ],
                [
                    0.5070281124497992,
                    0.40662650602409633
                ],
                [
                    0.4608433734939759,
                    0.3780120481927711
                ],
                [
                    0.7449799196787149,
                    0.34789156626506024
                ],
                [
                    0.7387048192771084,
                    0.3413654618473896
                ],
                [
                    0.7178714859437751,
                    0.33835341365461846
                ],
                [
                    0.7009705488621151,
                    0.34036144578313254
                ],
                [
                    0.7023092369477911,
                    0.33032128514056225
                ],
                [
                    0.6982931726907631,
                    0.32530120481927716
                ],
                [
                    0.6987951807228916,
                    0.3192771084337349
                ],
                [
                    0.7018072289156626,
                    0.3132530120481928
                ],
                [
                    0.7055722891566265,
                    0.3104919678714859
                ],
                [
                    0.9841867469879518,
                    0.34387550200803213
                ],
                [
                    0.9874497991967871,
                    0.33584337349397586
                ],
                [
                    0.9919678714859438,
                    0.33232931726907633
                ],
                [
                    0.9928045515394913,
                    0.3217871485943775
                ],
                [
                    0.9839357429718876,
                    0.321285140562249
                ],
                [
                    0.9984939759036144,
                    0.31726907630522083
                ],
                [
                    0.9909638554216867,
                    0.31475903614457834
                ],
                [
                    0.9815930388219544,
                    0.3140896921017403
                ],
                [
                    0.9759036144578314,
                    0.30773092369477917
                ],
                [
                    0.9687081659973226,
                    0.30471887550200805
                ],
                [
                    0.9994979919678715,
                    0.2956827309236948
                ],
                [
                    0.9779116465863453,
                    0.29718875502008035
                ],
                [
                    0.9688755020080321,
                    0.29969879518072284
                ],
                [
                    0.9641064257028112,
                    0.2969377510040161
                ],
                [
                    0.982429718875502,
                    0.2906626506024096
                ],
                [
                    0.9829317269076305,
                    0.285140562248996
                ],
                [
                    0.9929718875502008,
                    0.2735943775100401
                ],
                [
                    0.9919678714859438,
                    0.2680722891566265
                ],
                [
                    0.3674698795180723,
                    0.23393574297188757
                ],
                [
                    0.3709839357429719,
                    0.22891566265060237
                ],
                [
                    0.3709839357429719,
                    0.22389558232931728
                ],
                [
                    0.3684738955823293,
                    0.21787148594377514
                ],
                [
                    0.3684738955823293,
                    0.2088353413654619
                ],
                [
                    0.36596385542168675,
                    0.2038152610441767
                ],
                [
                    0.3679718875502008,
                    0.19829317269076308
                ],
                [
                    0.36596385542168675,
                    0.18825301204819278
                ],
                [
                    0.36997991967871485,
                    0.18222891566265065
                ],
                [
                    0.36872489959839355,
                    0.17595381526104414
                ],
                [
                    0.3704819277108434,
                    0.1711847389558233
                ],
                [
                    0.37851405622489964,
                    0.1647701918786256
                ],
                [
                    0.35642570281124497,
                    0.17520080321285136
                ],
                [
                    0.3770080321285141,
                    0.1736947791164659
                ],
                [
                    0.38403614457831325,
                    0.16214859437751006
                ],
                [
                    0.3463855421686747,
                    0.17218875502008035
                ],
                [
                    0.3865461847389558,
                    0.17520080321285136
                ],
                [
                    0.39006024096385544,
                    0.17720883534136544
                ],
                [
                    0.3865461847389558,
                    0.1531124497991968
                ],
                [
                    0.39056224899598396,
                    0.15110441767068272
                ],
                [
                    0.39608433734939763,
                    0.17846385542168675
                ],
                [
                    0.5306224899598394,
                    0.2319277108433735
                ],
                [
                    0.5170682730923695,
                    0.2269076305220884
                ],
                [
                    0.5040160642570282,
                    0.2118473895582329
                ],
                [
                    0.5030120481927711,
                    0.20582329317269077
                ],
                [
                    0.5050200803212851,
                    0.20230923694779113
                ],
                [
                    0.5055220883534136,
                    0.19277108433734935
                ],
                [
                    0.5020080321285141,
                    0.1837349397590361
                ],
                [
                    0.4959839357429719,
                    0.17971887550200805
                ],
                [
                    0.49497991967871485,
                    0.16716867469879515
                ],
                [
                    0.4899598393574297,
                    0.16641566265060243
                ],
                [
                    0.48493975903614456,
                    0.15913654618473894
                ],
                [
                    0.4884538152610442,
                    0.15210843373493976
                ],
                [
                    0.49497991967871485,
                    0.15160642570281124
                ],
                [
                    0.5085341365461847,
                    0.14658634538152615
                ],
                [
                    0.5346385542168675,
                    0.1480923694779116
                ],
                [
                    0.5471887550200804,
                    0.14206827309236947
                ],
                [
                    0.5562248995983936,
                    0.1430722891566265
                ],
                [
                    0.19879518072289157,
                    0.20030120481927716
                ],
                [
                    0.19427710843373494,
                    0.19678714859437751
                ],
                [
                    0.18122489959839358,
                    0.19327309236947787
                ],
                [
                    0.16792168674698796,
                    0.1950301204819277
                ],
                [
                    0.16917670682730923,
                    0.19979919678714864
                ],
                [
                    0.16039156626506024,
                    0.19151606425702816
                ],
                [
                    0.16014056224899598,
                    0.18724899598393574
                ],
                [
                    0.15461847389558234,
                    0.18975903614457834
                ],
                [
                    0.1576305220883534,
                    0.1837349397590361
                ],
                [
                    0.33032128514056225,
                    0.1300200803212851
                ],
                [
                    0.33383534136546184,
                    0.12437248995983935
                ],
                [
                    0.3324966532797858,
                    0.11211512717536813
                ],
                [
                    0.338855421686747,
                    0.10742971887550201
                ],
                [
                    0.33634538152610444,
                    0.0993975903614458
                ],
                [
                    0.3371820615796519,
                    0.08199464524765732
                ],
                [
                    0.3348393574297189,
                    0.07530120481927716
                ],
                [
                    0.3461345381526104,
                    0.08007028112449799
                ],
                [
                    0.3458835341365462,
                    0.07429718875502012
                ],
                [
                    0.3356760374832664,
                    0.0625
                ],
                [
                    0.3406124497991968,
                    0.06752008032128509
                ],
                [
                    0.3393574297188755,
                    0.05923694779116462
                ],
                [
                    0.33082329317269077,
                    0.06224899598393574
                ],
                [
                    0.34437751004016065,
                    0.05773092369477917
                ],
                [
                    0.33383534136546184,
                    0.04769076305220887
                ],
                [
                    0.33825301204819275,
                    0.04447791164658634
                ],
                [
                    0.3345883534136546,
                    0.03890562248995988
                ],
                [
                    0.3313253012048193,
                    0.034136546184738936
                ],
                [
                    0.33082329317269077,
                    0.026606425702811243
                ],
                [
                    0.3232931726907631,
                    0.029618473895582365
                ],
                [
                    0.3473895582329317,
                    0.026104417670682722
                ],
                [
                    0.3273092369477912,
                    0.0230923694779116
                ],
                [
                    0.31877510040160645,
                    0.02416810097532986
                ],
                [
                    0.3509036144578313,
                    0.015060240963855387
                ],
                [
                    0.31977911646586343,
                    0.016566265060240948
                ],
                [
                    0.31977911646586343,
                    0.012048192771084376
                ],
                [
                    0.3514056224899598,
                    0.007028112449799173
                ],
                [
                    0.30873493975903615,
                    0.02459839357429716
                ],
                [
                    0.32379518072289154,
                    0.001506024096385561
                ],
                [
                    0.3017068273092369,
                    0.013554216867469826
                ],
                [
                    0.21260040160642568,
                    0.054467871485943786
                ],
                [
                    0.22188755020080322,
                    0.04919678714859432
                ],
                [
                    0.22439759036144577,
                    0.04467871485943775
                ],
                [
                    0.2354417670682731,
                    0.03514056224899598
                ],
                [
                    0.2371987951807229,
                    0.027861445783132543
                ],
                [
                    0.23744979919678716,
                    0.02359437751004012
                ],
                [
                    0.23142570281124497,
                    0.027108433734939763
                ],
                [
                    0.2319277108433735,
                    0.013052208835341417
                ],
                [
                    0.4036144578313253,
                    0.01757028112449799
                ],
                [
                    0.40612449799196787,
                    0.008366800535475227
                ],
                [
                    0.4006024096385542,
                    0.004518072289156572
                ],
                [
                    0.4086345381526104,
                    0.003514056224899642
                ],
                [
                    0.41365461847389556,
                    0.0005020080321285203
                ],
                [
                    0.392570281124498,
                    0.004016064257028162
                ],
                [
                    0.3865461847389558,
                    0.0060240963855421326
                ],
                [
                    0.3820281124497992,
                    0.009538152610441775
                ],
                [
                    0.37751004016064255,
                    0.010040160642570295
                ]
            ],
            "clusters": [
                [
                    0,
                    1,
                    2,
                    4
                ],
                [
                    3
                ],
                [
                    5,
                    6
                ],
                [
                    7
                ],
                [
                    8,
                    9
                ],
                [
                    10,
                    11,
                    12,
                    16,
                    15,
                    13,
                    14,
                    17
                ],
                [
                    18
                ],
                [
                    19,
                    20,
                    21,
                    22
                ],
                [
                    23,
                    24,
                    26
                ],
                [
                    25
                ],
                [
                    27
                ],
                [
                    28,
                    29
                ],
                [
                    30,
                    32,
                    31,
                    33
                ],
                [
                    34,
                    35,
                    36,
                    37
                ],
                [
                    38,
                    40,
                    41,
                    39,
                    42,
                    44,
                    45,
                    49,
                    47,
                    46
                ],
                [
                    43,
                    48,
                    50,
                    51
                ],
                [
                    52,
                    53
                ],
                [
                    54,
                    55
                ],
                [
                    56,
                    57,
                    58
                ],
                [
                    59
                ],
                [
                    60
                ],
                [
                    61,
                    62,
                    63,
                    64,
                    65
                ],
                [
                    66,
                    67
                ],
                [
                    68
                ],
                [
                    69,
                    70,
                    72,
                    71,
                    73,
                    74
                ],
                [
                    75
                ],
                [
                    76,
                    77,
                    78
                ],
                [
                    79,
                    80
                ],
                [
                    81,
                    82
                ]
            ]
        },
        "fractalDimension": 1.024383285511066,
        "linesInImage": 83,
        "clustersInImage": 29,
        "linesInCluster": [
            4,
            1,
            2,
            1,
            2,
            8,
            1,
            4,
            3,
            1,
            1,
            2,
            4,
            4,
            10,
            4,
            2,
            2,
            3,
            1,
            1,
            5,
            2,
            1,
            6,
            1,
            3,
            2,
            2
        ],
        "averageLineLength": [
            0.018448131869563875,
            0.03782719061276758,
            0.017829190702839323,
            0.0694294391656323,
            0.0594992632943376,
            0.032779159182414544,
            0.06338846548659564,
            0.03192231980926374,
            0.029027172615362935,
            0.022721613004079308,
            0.02988986602883914,
            0.013903872535806903,
            0.013250288271248025,
            0.036380428134638945,
            0.01904310428178694,
            0.018412768121223503,
            0.030294750578260872,
            0.036038336493442825,
            0.023194118839652538,
            0.04512758475914483,
            0.010533535749624727,
            0.028717973152287784,
            0.08777552922045931,
            0.03265949352204382,
            0.023615778642315326,
            0.037741193847201704,
            0.022575141950985405,
            0.02705176392822936,
            0.021358111298610236
        ],
        "sinuosity": [
            1.0175243765082667,
            1.352782024356278,
            1.0,
            1.1482694285206443,
            1.0268168511778186,
            1.0011289640800833,
            1.2031599938286703,
            1.0352171390138656,
            1.066443469302257,
            1.1295484635143798,
            1.0678071823282118,
            1.0736720530591766,
            1.0,
            1.0544036266047605,
            1.158031979194917,
            1.0228375232150366,
            1.0135970784737869,
            1.015325750161441,
            1.3031364812744362,
            1.0379386799299244,
            1.3692422986801815,
            1.0,
            1.0,
            1.0044717594651844,
            1.0,
            1.1148005897686037,
            1.0278569649836644,
            1.100880189762789,
            1.0,
            1.483709585652624,
            1.0050373463601323,
            1.149152819574205,
            1.1015431585676811,
            1.0,
            1.1246233285838556,
            1.0107888021852494,
            1.2200578943927125,
            1.0789639680417031,
            1.0269213829705544,
            1.0748299970294797,
            1.0,
            1.1711119691247238,
            1.0,
            1.0,
            1.239574308869609,
            1.0000164499626807,
            1.0635152113841466,
            1.0672387552835616,
            1.0066229222260576,
            1.0,
            1.0778378887679403,
            1.0,
            1.0217247392282929,
            1.0,
            1.0085337418922398,
            1.1252418760142806,
            1.0530904901025697,
            1.2096114384511905,
            1.0450674549418015,
            1.0546627695925475,
            1.1652119059370467,
            1.0703763666309445,
            1.006623254451367,
            1.0335660044962651,
            1.0489013919831753,
            1.0967541404431689,
            1.1502530566746485,
            1.2363283214576706,
            1.0427602534564608,
            1.0,
            1.106750729460685,
            1.0187881598924047,
            1.563041070717117,
            1.3600474188915501,
            1.1197575325917266,
            1.0471567485925368,
            1.317626914800225,
            1.0110166451669813,
            1.1512930462392872,
            1.046725547070269,
            1.02900704435472,
            1.0394376003194028,
            1.095419618008553
        ],
        "centerLineWidth": [
            0.0050200803212851405,
            0.023092369477911646,
            0.008032128514056224,
            0.004016064257028112,
            0.004518072289156626,
            0.008032128514056224,
            0.007028112449799197,
            0.0050200803212851405,
            0.0050200803212851405,
            0.007530120481927711,
            0.004518072289156626,
            0.007530120481927711,
            0.009036144578313253,
            0.004016064257028112,
            0.007530120481927711,
            0.004016064257028112,
            0.004518072289156626,
            0.0035140562248995983,
            0.007028112449799197,
            0.004016064257028112,
            0.004016064257028112,
            0.016566265060240965,
            0.002008032128514056,
            0.0030120481927710845,
            0.006526104417670682,
            0.0035140562248995983,
            0.005522088353413655,
            0.0050200803212851405,
            0.015060240963855422,
            0.012048192771084338,
            0.005522088353413655,
            0.0030120481927710845,
            0.0050200803212851405,
            0.004016064257028112,
            0.004518072289156626,
            0.004518072289156626,
            0.006024096385542169,
            0.0030120481927710845,
            0.0035140562248995983,
            0.0050200803212851405,
            0.01857429718875502,
            0.026606425702811246,
            0.0025100401606425703,
            0.029116465863453816,
            0.009538152610441768,
            0.0321285140562249,
            0.005522088353413655,
            0.0035140562248995983,
            0.004016064257028112,
            0.00853413654618474,
            0.0050200803212851405,
            0.002008032128514056,
            0.006024096385542169,
            0.0030120481927710845,
            0.0035140562248995983,
            0.0050200803212851405,
            0.038654618473895584,
            0.014056224899598393,
            0.0050200803212851405,
            0.0035140562248995983,
            0.0035140562248995983,
            0.004518072289156626,
            0.0030120481927710845,
            0.009538152610441768,
            0.0035140562248995983,
            0.007028112449799197,
            0.0050200803212851405,
            0.004016064257028112,
            0.005522088353413655,
            0.007028112449799197,
            0.004016064257028112,
            0.006526104417670682,
            0.006024096385542169,
            0.02208835341365462,
            0.004016064257028112,
            0.004016064257028112,
            0.004518072289156626,
            0.004016064257028112,
            0.006024096385542169,
            0.002008032128514056,
            0.007028112449799197,
            0.005522088353413655,
            0.0030120481927710845
        ],
        "lineComments": {},
        "clusterComments": {}
    },
    "network": {
        "skeleton": "/Users/melaniemadrigal/Desktop/Skeleton3/C5_008_network.tif",
        "vectorized": {
            "lines": [],
            "points": [],
            "clusters": []
        },
        "fractalDimension": 0.0,
        "linesInImage": 0,
        "clustersInImage": 0,
        "linesInCluster": [],
        "averageLineLength": [],
        "sinuosity": [],
        "centerLineWidth": [],
        "lineComments": {},
        "clusterComments": {}
    }
}